setup.py
hf_bi/setup.py
hf_bi/test.py
hf_bi.egg-info/PKG-INFO
hf_bi.egg-info/SOURCES.txt
hf_bi.egg-info/dependency_links.txt
hf_bi.egg-info/not-zip-safe
hf_bi.egg-info/top_level.txt