Metadata-Version: 1.0
Name: hf-bi
Version: 0.0.1
Summary: HelloFresh BI library
Home-page: https://github.com/welfare520/hf_bi.git
Author: He Zhang
Author-email: hz@hellofresh.com
License: MIT
Platform: UNKNOWN
